rfb_driver_db/__init__.py
rfb_driver_db/__version__.py
rfb_driver_db/context.py
rfb_driver_db/drv_db_dao_base.py
rfb_driver_db/drv_db_dao_cache.py
rfb_driver_db/drv_db_dao_master.py
rfb_driver_db/drv_db_dao_utils.py
rfb_driver_db/drv_db_engine.py
rfb_driver_db/drv_db_types.py
rfb_driver_db-0.0.2.dist-info/LICENSE.txt
rfb_driver_db-0.0.2.dist-info/METADATA
rfb_driver_db-0.0.2.dist-info/WHEEL
rfb_driver_db-0.0.2.dist-info/top_level.txt
rfb_driver_db-0.0.2.dist-info/RECORD
