Metadata-Version: 2.1
Name: rfb_driver_db
Version: 0.0.2
Summary: A simple database connector for SQLAlchemy. It is used to 
Author-email: Javier Sanz <javiersanzmoline@gmail.com>, Raldea <r.aldea.csic+pypi@gmail.com>, Marius Crisan <mariuscrsn+pypi@gmail.com>, Pablo Pastor <pastorpflores+pypi@gmail.com>, Luis Roche <luis.roche@hotmail.com>
License: GNU GENERAL PUBLIC LICENSE
Project-URL: Homepage, https://github.com/GIDEF-RFB/Battery-Cycler-Drivers
Project-URL: Bug Reports, https://github.com/GIDEF-RFB/Battery-Cycler-Drivers/issues
Project-URL: Bug Tracker, https://github.com/GIDEF-RFB/Battery-Cycler-Drivers/issues
Project-URL: Source, https://github.com/GIDEF-RFB/Battery-Cycler-Drivers/code/drv_db
Project-URL: Funding, https://donate.pypi.org
Keywords: ORM,database,connector,mysql,sqlite,SQLAlchemy,Database abstraction
Classifier: Development Status :: 3 - Alpha
Classifier: Topic :: Software Development :: Embedded Systems
Classifier: Topic :: Database :: Front-Ends
Classifier: Topic :: Software Development :: Libraries :: Python Modules
Classifier: Operating System :: OS Independent
Classifier: License :: OSI Approved :: GNU Affero General Public License v3
Classifier: Programming Language :: Python :: 3
Classifier: Programming Language :: Python :: 3.7
Classifier: Programming Language :: Python :: 3.8
Classifier: Programming Language :: Python :: 3.9
Classifier: Programming Language :: Python :: 3.10
Classifier: Programming Language :: Python :: 3.11
Classifier: Programming Language :: Python :: 3 :: Only
Classifier: Programming Language :: SQL
Requires-Python: >=3.7
License-File: LICENSE.txt
Requires-Dist: mysql-connector-python >=8.0.33
Requires-Dist: SQLAlchemy >=2.0.23
Requires-Dist: rfb-config-tool >=0.0.1
Requires-Dist: rfb-logger-tool >=0.0.1
